shibari.py
shibari-0.0.2.dist-info/DESCRIPTION.rst
shibari-0.0.2.dist-info/METADATA
shibari-0.0.2.dist-info/RECORD
shibari-0.0.2.dist-info/WHEEL
shibari-0.0.2.dist-info/metadata.json
shibari-0.0.2.dist-info/top_level.txt
