Metadata-Version: 2.0
Name: shibari
Version: 0.0.2
Summary: Bind functions to run only once inside a desired scope.
Home-page: https://github.com/jsfehler/shibari
Author: Joshua Fehler
Author-email: jsfehler@gmail.com
License: MIT
Platform: UNKNOWN
Classifier: Programming Language :: Python :: 3.6
Classifier: Programming Language :: Python :: 3.7
Classifier: Programming Language :: Python :: 3.8
Classifier: License :: OSI Approved :: MIT License
Classifier: Operating System :: OS Independent
Classifier: Development Status :: 4 - Beta
